MANIFEST.in
README.md
setup.py
singtown_ai_mock_server/__init__.py
singtown_ai_mock_server/__main__.py
singtown_ai_mock_server/train.py
singtown_ai_mock_server.egg-info/PKG-INFO
singtown_ai_mock_server.egg-info/SOURCES.txt
singtown_ai_mock_server.egg-info/dependency_links.txt
singtown_ai_mock_server.egg-info/requires.txt
singtown_ai_mock_server.egg-info/top_level.txt
singtown_ai_mock_server/media/images/cat.0.jpg
singtown_ai_mock_server/media/images/cat.1.jpg
singtown_ai_mock_server/media/images/cat.10.jpg
singtown_ai_mock_server/media/images/cat.100.jpg
singtown_ai_mock_server/media/images/cat.101.jpg
singtown_ai_mock_server/media/images/cat.102.jpg
singtown_ai_mock_server/media/images/cat.103.jpg
singtown_ai_mock_server/media/images/cat.104.jpg
singtown_ai_mock_server/media/images/cat.105.jpg
singtown_ai_mock_server/media/images/cat.106.jpg
singtown_ai_mock_server/media/images/cat.107.jpg
singtown_ai_mock_server/media/images/cat.108.jpg
singtown_ai_mock_server/media/images/cat.109.jpg
singtown_ai_mock_server/media/images/cat.11.jpg
singtown_ai_mock_server/media/images/cat.110.jpg
singtown_ai_mock_server/media/images/cat.111.jpg
singtown_ai_mock_server/media/images/cat.112.jpg
singtown_ai_mock_server/media/images/cat.113.jpg
singtown_ai_mock_server/media/images/cat.114.jpg
singtown_ai_mock_server/media/images/cat.115.jpg
singtown_ai_mock_server/media/images/cat.116.jpg
singtown_ai_mock_server/media/images/cat.117.jpg
singtown_ai_mock_server/media/images/cat.118.jpg
singtown_ai_mock_server/media/images/cat.119.jpg
singtown_ai_mock_server/media/images/cat.12.jpg
singtown_ai_mock_server/media/images/cat.120.jpg
singtown_ai_mock_server/media/images/cat.121.jpg
singtown_ai_mock_server/media/images/cat.122.jpg
singtown_ai_mock_server/media/images/cat.123.jpg
singtown_ai_mock_server/media/images/cat.124.jpg
singtown_ai_mock_server/media/images/cat.125.jpg
singtown_ai_mock_server/media/images/cat.126.jpg
singtown_ai_mock_server/media/images/cat.127.jpg
singtown_ai_mock_server/media/images/cat.128.jpg
singtown_ai_mock_server/media/images/cat.129.jpg
singtown_ai_mock_server/media/images/cat.13.jpg
singtown_ai_mock_server/media/images/cat.130.jpg
singtown_ai_mock_server/media/images/cat.131.jpg
