Metadata-Version: 2.2
Name: singtown_ai_mock_server
Version: 0.4.2
Requires-Dist: Flask
Requires-Dist: singtown_ai
Dynamic: requires-dist
